stat_tracker/__init__.py
stat_tracker-0.1.0.dist-info/LICENSE
stat_tracker-0.1.0.dist-info/METADATA
stat_tracker-0.1.0.dist-info/WHEEL
stat_tracker-0.1.0.dist-info/top_level.txt
stat_tracker-0.1.0.dist-info/RECORD
