Metadata-Version: 2.1
Name: stat-tracker
Version: 0.1.0
Summary: Local metrics and measurements
Author-email: David Kincaid <daelonsuzuka@gmail.com>
License: MIT License
Project-URL: Homepage, https://github.com/DaelonSuzuka/stat_tracker
Project-URL: Repository, https://github.com/DaelonSuzuka/stat_tracker
Project-URL: Issues, https://github.com/DaelonSuzuka/stat_tracker/issues
Classifier: Development Status :: 4 - Beta
Classifier: Intended Audience :: Developers
Classifier: Operating System :: OS Independent
Classifier: License :: OSI Approved :: MIT License
Classifier: Programming Language :: Python :: 3
Classifier: Programming Language :: Python :: 3.9
Classifier: Programming Language :: Python :: 3.10
Classifier: Programming Language :: Python :: 3.11
Classifier: Programming Language :: Python :: 3.12
Classifier: Programming Language :: Python :: 3.13
Requires-Python: >=3.9
License-File: LICENSE
